snakestack/__init__.py
snakestack/config.py
snakestack/constants.py
snakestack/py.typed
snakestack/version.py
snakestack/cache/__init__.py
snakestack/cache/async_client.py
snakestack/cache/async_service.py
snakestack/cache/settings.py
snakestack/cache/utils.py
snakestack/healthz/__init__.py
snakestack/healthz/healthz.py
snakestack/healthz/model.py
snakestack/httpx/__init__.py
snakestack/httpx/client.py
snakestack/httpx/exceptions.py
snakestack/logging/__init__.py
snakestack/logging/config.py
snakestack/logging/contexts.py
snakestack/logging/encoders.py
snakestack/logging/filters.py
snakestack/logging/formatters.py
snakestack/logging/settings.py
snakestack/model/__init__.py
snakestack/model/base.py
snakestack/model/doc.py
snakestack/model/error.py
snakestack/model/lenient.py
snakestack/model/orm.py
snakestack/model/pagination.py
snakestack/mongodb/__init__.py
snakestack/mongodb/async_client.py
snakestack/mongodb/settings.py
snakestack/pubsub/__init__.py
snakestack/pubsub/exceptions.py
snakestack/pubsub/settings.py
snakestack/pubsub/publisher/__init__.py
snakestack/pubsub/publisher/client.py
snakestack/pubsub/publisher/factory.py
snakestack/pubsub/subscriber/__init__.py
snakestack/pubsub/subscriber/batch.py
snakestack/pubsub/subscriber/client.py
snakestack/pubsub/subscriber/exceptions.py
snakestack/pubsub/subscriber/factory.py
snakestack/pubsub/subscriber/processors.py
snakestack/pubsub/subscriber/signals.py
snakestack/pubsub/subscriber/telemetry.py
snakestack/pubsub/subscriber/types.py
snakestack/pubsub/subscriber/utils.py
snakestack/task/__init__.py
snakestack/task/process.py
snakestack/telemetry/__init__.py
snakestack/telemetry/helpers.py
snakestack/telemetry/instrumentor.py
snakestack/telemetry/settings.py
snakestack-0.21.0.dist-info/licenses/LICENSE
snakestack-0.21.0.dist-info/METADATA
snakestack-0.21.0.dist-info/WHEEL
snakestack-0.21.0.dist-info/top_level.txt
snakestack-0.21.0.dist-info/RECORD
