Metadata-Version: 2.4
Name: snakestack
Version: 0.21.0
Summary: Uma coleção de utilitários para acelerar o desenvolvimento backend em Python com padrões reutilizáveis e produtivos
Author-email: Bruno Segato <brunosegatoit@gmail.com>
Requires-Python: <4.0,>=3.10
License-File: LICENSE
Requires-Dist: httpx>=0.28.1
Requires-Dist: orjson>=3.11.2
Requires-Dist: pydantic-settings>=2.10.1
Provides-Extra: mongodb
Requires-Dist: motor>=3.7.1; extra == "mongodb"
Provides-Extra: redis
Requires-Dist: redis>=6.4.0; extra == "redis"
Provides-Extra: pubsub
Requires-Dist: google-cloud-pubsub>=2.31.1; extra == "pubsub"
Provides-Extra: telemetry
Requires-Dist: opentelemetry-api>=1.36.0; extra == "telemetry"
Requires-Dist: opentelemetry-exporter-otlp>=1.36.0; extra == "telemetry"
Requires-Dist: opentelemetry-instrumentation-grpc>=0.57b0; extra == "telemetry"
Requires-Dist: opentelemetry-instrumentation-httpx>=0.57b0; extra == "telemetry"
Requires-Dist: opentelemetry-instrumentation-logging>=0.57b0; extra == "telemetry"
Dynamic: license-file
